{
  "circuit": {
    "type": "serie",
    "voltage": "VOLTAGE_ELEVE",
    "protection": { "type": "DISJONCTEUR", "valeur": 60 },
    "interrupteurAllume": true,
    "composants": [
      { "type": "resistance", "valeur": 20, "voltage": "VOLTAGE_ELEVE" },
      {
        "type": "parallele",
        "voltage": "VOLTAGE_ELEVE",
        "interrupteurAllume": true,
        "composants": [
          {
            "type": "serie",
            "voltage": "VOLTAGE_STANDARD",
            "composants": [
              { "type": "resistance", "valeur": 10, "voltage": "VOLTAGE_STANDARD" },
              { "type": "resistance", "valeur": 6, "voltage": "VOLTAGE_STANDARD" }
            ]
          },
          {
            "type": "serie",
            "voltage": "VOLTAGE_BAS",
            "interrupteurAllume": true,
            "composants": [
              {
                "type": "charge",
                "nom": "Projecteur",
                "valeur": 3,
                "voltage": "VOLTAGE_BAS",
                "typeEnergie": "RAYONNANTE"
              },
              {
                "type": "parallele",
                "voltage": "VOLTAGE_BAS",
                "composants": [
                  {
                    "type": "charge",
                    "nom": "Four de test",
                    "valeur": 2,
                    "voltage": "VOLTAGE_BAS",
                    "typeEnergie": "THERMIQUE"
                  },
                  { "type": "resistance", "valeur": 4, "voltage": "VOLTAGE_BAS" }
                ]
              }
            ]
          },
          {
            "type": "charge",
            "nom": "Centrale",
            "valeur": 50,
            "voltage": "VOLTAGE_ELEVE",
            "typeEnergie": "NUCLEAIRE"
          }
        ]
      },
      { "type": "resistance", "valeur": 10, "voltage": "VOLTAGE_ELEVE" }
    ]
  }
}
